tunneler/__init__.py
tunneler/command.py
tunneler/connect.py
tunneler/tasks.py
tunneler/util.py
tunneler-0.1.1490760674.dist-info/DESCRIPTION.rst
tunneler-0.1.1490760674.dist-info/METADATA
tunneler-0.1.1490760674.dist-info/RECORD
tunneler-0.1.1490760674.dist-info/WHEEL
tunneler-0.1.1490760674.dist-info/entry_points.txt
tunneler-0.1.1490760674.dist-info/metadata.json
tunneler-0.1.1490760674.dist-info/top_level.txt
