Metadata-Version: 2.0
Name: tunneler
Version: 0.1.1490760674
Summary: Connect to databases via ssh tunnel
Home-page: https://github.com/govau/tunneler
Author: Robert Lechte
Author-email: robert.lechte@digital.gov.au
License: UNKNOWN
Platform: UNKNOWN
Classifier: Development Status :: 3 - Alpha
Classifier: Intended Audience :: Developers
Classifier: Natural Language :: English
Classifier: Programming Language :: Python
Classifier: Programming Language :: Python :: 2.7
Classifier: Programming Language :: Python :: 3
Classifier: Programming Language :: Python :: 3.6
Classifier: Programming Language :: Python :: Implementation :: CPython
Requires-Dist: paramiko
Requires-Dist: pyyaml
Requires-Dist: six
Requires-Dist: sqlbag
Requires-Dist: sshtunnel
Provides-Extra: pg
Requires-Dist: psycopg2; extra == 'pg'
